memtrace2npz/__init__.py
memtrace2npz-0.0.1.data/scripts/memtrace2npz
memtrace2npz-0.0.1.dist-info/LICENSE
memtrace2npz-0.0.1.dist-info/METADATA
memtrace2npz-0.0.1.dist-info/WHEEL
memtrace2npz-0.0.1.dist-info/top_level.txt
memtrace2npz-0.0.1.dist-info/RECORD
