Metadata-Version: 2.1
Name: memtrace2npz
Version: 0.0.1
Summary: A package for converting binary output of DynamoRIO's memtrace client to npz.
Home-page: https://github.com/plavin/memtrace2npz
Author: Patrick Lavin
Author-email: plavin997@gmail.com
License: UNKNOWN
Project-URL: Bug Tracker, https://github.com/plavin/memtrace2npz/issues
Platform: UNKNOWN
Classifier: Programming Language :: Python :: 3
Classifier: License :: OSI Approved :: GNU General Public License v3 (GPLv3)
Classifier: Operating System :: OS Independent
Requires-Python: >=3.6
Requires-Dist: numpy
Requires-Dist: pytest
